fosslight_android/__init__.py
fosslight_android/_binary_db_controller.py
fosslight_android/_common.py
fosslight_android/_help.py
fosslight_android/_src_analysis.py
fosslight_android/_util.py
fosslight_android/android_binary_analysis.py
fosslight_android/check_notice_file.py
fosslight_android/check_package_file.py
fosslight_android/resources/aosp_repository.json
fosslight_android/resources/module_license.json
fosslight_android-5.0.11.dist-info/LICENSE
fosslight_android-5.0.11.dist-info/METADATA
fosslight_android-5.0.11.dist-info/WHEEL
fosslight_android-5.0.11.dist-info/entry_points.txt
fosslight_android-5.0.11.dist-info/top_level.txt
fosslight_android-5.0.11.dist-info/RECORD
