Metadata-Version: 2.1
Name: fosslight-android
Version: 5.0.11
Summary: FOSSLight Android Scanner
Home-page: https://github.com/fosslight/fosslight_android_scanner
Download-URL: https://github.com/fosslight/fosslight_android_scanner
Author: LG Electronics
License: Apache-2.0
Classifier: License :: OSI Approved :: Apache Software License
Classifier: Programming Language :: Python :: 3
Classifier: Programming Language :: Python :: 3.10
Classifier: Programming Language :: Python :: 3.11
Classifier: Programming Language :: Python :: 3.12
Requires-Python: >=3.10, <3.13
License-File: LICENSE
Requires-Dist: fosslight-util~=2.1.8
Requires-Dist: fosslight-source~=2.1.0
Requires-Dist: fosslight-binary~=5.1.0
Requires-Dist: beautifulsoup4
Requires-Dist: lxml
Requires-Dist: numpy
Requires-Dist: pandas
Requires-Dist: parmap
Requires-Dist: psycopg2-binary
Requires-Dist: python-dateutil
Requires-Dist: py-tlsh
Requires-Dist: pytz
Requires-Dist: six
Requires-Dist: soupsieve
Requires-Dist: tqdm
Requires-Dist: urlopen
Requires-Dist: XlsxWriter
Requires-Dist: PyYAML
